pycounts_merari_524/__init__.py
pycounts_merari_524/plotting.py
pycounts_merari_524/pycounts_merari_524.py
pycounts_merari_524-0.1.0.dist-info/LICENSE
pycounts_merari_524-0.1.0.dist-info/METADATA
pycounts_merari_524-0.1.0.dist-info/WHEEL
pycounts_merari_524-0.1.0.dist-info/RECORD
